pytm/__init__.py
pytm/json.py
pytm/pytm.py
pytm/report_util.py
pytm/template_engine.py
pytm/images/datastore.png
pytm/images/datastore_black.png
pytm/images/datastore_darkgreen.png
pytm/images/datastore_firebrick3.png
pytm/images/datastore_gold.png
pytm/images/lambda.png
pytm/threatlib/threats.json
pytm-1.3.1.dist-info/LICENSE
pytm-1.3.1.dist-info/METADATA
pytm-1.3.1.dist-info/WHEEL
pytm-1.3.1.dist-info/top_level.txt
pytm-1.3.1.dist-info/RECORD
